camo_sign/__init__.py
camo_sign-0.1.1.dist-info/DESCRIPTION.rst
camo_sign-0.1.1.dist-info/METADATA
camo_sign-0.1.1.dist-info/RECORD
camo_sign-0.1.1.dist-info/WHEEL
camo_sign-0.1.1.dist-info/metadata.json
camo_sign-0.1.1.dist-info/top_level.txt
