Metadata-Version: 2.0
Name: camo-sign
Version: 0.1.1
Summary: Generate signed URLs for Camo image proxy
Home-page: https://github.com/bkno3/camo-sign
Author: Samuele Santi
Author-email: samuele+gh@samuelesanti.com
License: BSD License
Platform: UNKNOWN
Classifier: License :: OSI Approved :: BSD License
Classifier: Programming Language :: Python :: 3.3
Classifier: Programming Language :: Python :: 3.4
Classifier: Programming Language :: Python :: 3.5
Classifier: Programming Language :: Python :: 3.6
Classifier: Programming Language :: Python :: 3 :: Only
